emzed_ext_test2/__init__.py
emzed_ext_test2/example_module.py
emzed_ext_test2/data/readme.txt
emzed_ext_test2-0.0.1.dist-info/LICENSE.txt
emzed_ext_test2-0.0.1.dist-info/METADATA
emzed_ext_test2-0.0.1.dist-info/WHEEL
emzed_ext_test2-0.0.1.dist-info/top_level.txt
emzed_ext_test2-0.0.1.dist-info/RECORD
