Metadata-Version: 2.1
Name: emzed-ext-test2
Version: 0.0.1
Summary: please describe the package here in one line
Home-page: https://www.ethz.ch
Author: Jane Everybody
Author-email: jane.everybodyf@ethz.ch
License: http://opensource.org/licenses/GPL-3.0
License-File: LICENSE.txt
Requires-Dist: emzed >=3.0.0a1
Requires-Dist: emzed-gui >=3.0.0a1
